{"text_id":107210,"tokens":["If"," you","'","re"," playing"," Pok\u00e9mon"," Gold",","," Silver",","," or"," Crystal",","," and"," you","'","re"," trying"," to"," catch"," yourself"," a"," Cele","bi",","," there"," are"," a"," few"," things"," you"," should"," know",".","\n\n","First",","," you"," should"," make"," sure"," that"," you"," have"," the"," right"," game","."," Cele","bi"," is"," only"," available"," in"," Gold",","," Silver",","," and"," Crystal",","," so"," if"," you","'","re"," playing"," one"," of"," the"," other"," Pok\u00e9mon"," games",","," you"," won","'","t"," be"," able"," to"," find"," it",".","\n\n","Once"," you"," have"," the"," right"," game",","," you"," should"," make"," sure"," that"," you","'","re"," in"," the"," right"," place","."," Cele","bi"," can"," be"," found"," in"," the"," Hall"," of"," Fame",","," so"," if"," you"," haven","'","t"," beaten"," the"," game"," yet",","," you"," won","'","t"," be"," able"," to"," get"," it",".","\n\n","Finally",","," you"," should"," make"," sure"," that"," you"," have"," the"," right"," Pok\u00e9mon","."," Cele","bi"," is"," a"," Psychic","-","type"," Pok\u00e9mon",","," so"," you","'","ll"," need"," to"," have"," a"," Pok\u00e9mon"," that"," can"," counter"," that","."," A"," good"," choice"," would"," be"," a"," Dark","-","type"," Pok\u00e9mon",","," like"," U","mbre","on"," or"," Hyp","no",".","\n\n","Once"," you"," have"," all"," of"," that",","," you"," should"," be"," ready"," to"," go","."," Just"," head"," to"," the"," Hall"," of"," Fame"," and"," look"," for"," a"," young"," boy"," standing"," next"," to"," a"," tree","."," Talk"," to"," him"," and"," he","'","ll"," give"," you"," acess"," to"," the"," Cele","bi"," Census",".","\n\n","From"," there",","," you","'","ll"," need"," to"," go"," to"," the"," locations"," listed"," in"," the"," Census"," and"," find"," the"," hidden"," Cele","bi","."," Once"," you","'","ve"," found"," them"," all",","," return"," to"," the"," boy"," next"," to"," the"," tree"," and"," he","'","ll"," give"," you"," a"," Cele","bi"," of"," your"," own","."],"sub_source":"wikihow","model":"cohere","label":1}