{"text_id":116886,"tokens":["This"," paper"," considers"," different"," methods"," of"," producing"," adversarial"," examples"," for"," generative"," models"," such"," as"," V","AE"," and"," V","AE","GAN","."," Specifically",","," three"," methods"," are"," considered",":"," classification","-","based"," adversaries"," which"," uses"," a"," classifier"," on"," top"," of"," the"," hidden"," code",","," V","AE"," loss"," which"," directly"," uses"," the"," V","AE"," loss"," and"," the"," \"","latent"," attack","\""," which"," finds"," adversarial"," perturbation"," in"," the"," input"," so"," as"," to"," match"," the"," latent"," representation"," of"," a"," target"," input",".","\n\n","I"," think"," the"," problem"," that"," this"," paper"," considers"," is"," potentially"," useful"," and"," interesting"," to"," the"," community","."," To"," the"," best"," of"," my"," knowledge"," this"," is"," the"," first"," paper"," that"," considers"," adversarial"," examples"," for"," generative"," models","."," As"," I"," pointed"," out"," in"," my"," pre","-","review"," comments",","," there"," is"," also"," a"," concurrent"," work"," of"," \"","Ad","vers","arial"," Images"," for"," Vari","ational"," Auto","enco","ders","\""," that"," essentially"," proposes"," the"," same"," \"","latent"," attack","\""," idea"," of"," this"," paper"," with"," both"," L","2"," distance"," and"," KL"," divergence",".","\n\n","Novel","ty","/","original","ity",":"," I"," didn","'","t"," find"," the"," ideas"," of"," this"," paper"," very"," original","."," All"," the"," proposed"," three"," attacks"," are"," well","-","known"," and"," standard"," methods"," that"," here"," are"," applied"," to"," a"," new"," problem"," and"," this"," paper"," does"," not"," develop"," *","novel","*"," algorithms"," for"," attacking"," specifically"," *","gener","ative"," models","*."," However"," I"," still"," find"," it"," interesting"," to"," see"," how"," these"," standard"," methods"," compare"," in"," this"," new"," problem"," domain",".","\n\n","The"," clarity"," and"," presentation"," of"," the"," paper"," is"," very"," uns","atis","fying","."," The"," first"," version"," of"," the"," paper"," proposes"," the"," \"","classification","-","based"," adversaries","\""," and"," reports"," only"," negative"," results","."," In"," the"," second"," set"," of"," revisions",","," the"," core"," idea"," of"," the"," paper"," changes"," and"," almost"," an"," entirely"," new"," paper"," with"," a"," new"," co","-","author"," is"," submitted"," and"," the"," idea"," of"," \"","latent"," attack","\""," is"," proposed"," which"," works"," much"," better"," than"," the"," \"","classification","-","based"," adversaries","\"."," However",","," the"," authors"," try"," to"," keep"," around"," the"," materials"," of"," the"," first"," version",","," which"," results"," in"," a"," ","1","3"," page"," long"," paper",","," with"," different"," claims"," and"," unrelated"," set"," of"," experiments","."," \"","in"," our"," attempts"," to"," be"," thorough",","," we"," have"," had"," a"," hard"," time"," keeping"," the"," length"," down","\""," is"," not"," a"," valid"," excuse",".","\n\n","In"," short",","," the"," paper"," is"," investigating"," an"," interesting"," problem"," and"," apply"," and"," compare"," standard"," adversarial"," methods"," to"," this"," domain",","," but"," the"," novelty"," and"," the"," presentation"," of"," the"," paper"," is"," limited","."],"sub_source":"peerread","model":"human","label":0}