{"text_id":129098,"tokens":["The"," Massachusetts"," Institute"," of"," Technology"," (","MIT",")"," has"," announced"," a"," major"," breakthrough"," in"," artificial"," intelligence"," technology"," with"," the"," development"," of"," an"," incredibly"," small"," brain"," chip","."," This"," tiny"," chip",","," which"," is"," smaller"," than"," a"," penny",","," could"," soon"," bring"," the"," capabilities"," of"," super","computers"," to"," regular"," mobile"," devices","."," The"," new"," chip"," was"," developed"," by"," a"," team"," of"," researchers"," at"," MIT","'","s"," Computer"," Science"," and"," Artificial"," Intelligence"," Laboratory"," (","CSA","IL",")."," It"," is"," designed"," to"," mimic"," the"," way"," neurons"," work"," in"," the"," human"," brain",","," and"," it"," can"," process"," massive"," amounts"," of"," data"," in"," real","-","time","."," The"," chip"," is"," made"," up"," of"," several"," thousand"," transistors"," and"," micro","processors",","," and"," it"," is"," designed"," to"," be"," more"," energy","-","efficient"," than"," traditional"," chips","."," It"," is"," capable"," of"," performing"," deep"," learning"," tasks"," such"," as"," facial"," recognition"," and"," natural"," language"," processing",","," and"," it"," could"," even"," be"," used"," for"," self","-","driving"," cars","."," According"," to"," Professor"," Vivi","enne"," Sze",","," lead"," researcher"," on"," the"," project",","," \"","This"," chip"," could"," revolution","ize"," the"," way"," we"," interact"," with"," technology","."," We"," envision"," it"," being"," used"," in"," a"," range"," of"," applications",","," from"," robot"," navigation"," to"," medical"," diagnostics",".\""," The"," chip"," is"," still"," in"," its"," early"," stages"," of"," development",","," but"," the"," team"," believes"," that"," it"," will"," eventually"," be"," able"," to"," power"," much"," smarter"," mobile"," devices"," than"," what"," we"," have"," today","."," This"," could"," open"," a"," whole"," new"," world"," of"," possibilities"," for"," developers"," who"," are"," looking"," to"," create"," the"," next"," generation"," of"," AI","-","powered"," applications","."," It"," is"," expected"," that"," the"," chip"," will"," be"," ready"," for"," commercial"," use"," within"," the"," next"," few"," years","."," The"," team"," is"," now"," working"," on"," improving"," the"," chip","'","s"," performance"," and"," making"," it"," even"," more"," energy","-","efficient","."],"sub_source":"tldr","model":"text-davinci-003","label":1}