{"text_id":133486,"tokens":["It"," is"," a"," double"," replacement"," reaction"," in"," which"," two"," species"," exchange"," bonds",":"," A","-","B"," C","-","D"," -"," A","-","D"," C","-","B"," The"," products"," are"," in"," the"," same"," order"," as"," the"," reactants","."," Ammonia"," is"," not"," a"," product"," of"," this"," reaction",";"," however",","," it"," is"," an"," intermediate"," that"," is"," consumed"," in"," the"," reaction","."," H","Br"," and"," HNO","3"," are"," examples"," of"," strong"," acids","."],"sub_source":"eli5","model":"13B","label":1}