{"text_id":140711,"tokens":["In"," service"," computing",","," the"," same"," target"," functions"," can"," be"," achieved"," by"," multiple"," Web"," services"," from"," different"," providers","."," Due"," to"," the"," functional"," similarities",","," the"," client"," needs"," to"," consider"," the"," non","-","functional"," criteria","."," The"," performance"," of"," the"," web"," services"," in"," a"," given"," environment"," is"," a"," function"," of"," the"," number"," of"," clients"," provided"," and"," the"," bandwidth"," available"," for"," each"," web"," server","."," However",","," in"," certain"," environments"," where"," the"," deployment"," of"," various"," Web"," services"," on"," the"," same"," infrastructure"," may"," violate"," the"," availability"," guidelines"," or"," other"," requirements"," set"," forth"," above",","," the"," Web"," services"," may"," not"," perform"," as"," expected","."," Because"," many"," Web"," servers"," are"," coupled"," to"," multiple"," devices"," at"," once",","," the"," user"," may"," need"," to"," gather"," information"," about"," the"," virtual"," machine"," network"," (","V","MM","N",")"," of"," the"," V","MM","N"," and"," to"," decide"," how"," frequently"," such"," data"," will"," be"," gathered","."," Therefore",","," there"," exists"," a"," need"," for"," improved"," techniques"," for"," handling"," the"," collection"," of"," data"," related"," to"," web"," services"," that"," are"," not"," affected","."],"sub_source":"sci_gen","model":"opt_125m","label":1}