{"text_id":146010,"tokens":["Veronica"," yelled"," out"," her"," cat","'","s"," name"," from"," the"," window","."," She"," got"," the"," can"," opener"," in"," order"," to"," feed"," it"," as"," he"," hadn","'","t"," eaten"," yet","."," She"," looked"," up"," after"," the"," food"," was"," in"," the"," bowl"," and"," she"," saw"," Sn","uggles","."," He"," had"," impeccable"," timing",","," only"," showing"," up"," the"," moment"," food"," was"," ready","."," She"," pet","ted"," him"," behind"," the"," ears"," as"," he"," ate","."],"sub_source":"roct","model":"human","label":0}