{"text_id":149525,"tokens":["We"," investigate"," the"," distinction"," between"," supers","ymmetry"," and"," gauge"," symmetry"," in"," the"," context"," of"," the"," heter","otic"," string"," theory"," landscape","."," A"," long","-","standing"," problem"," in"," string"," phenomen","ology"," is"," the"," difficulty"," in"," constructing"," models"," that"," simultaneously"," accommodate"," both"," supers","ymmetry"," and"," gauge"," symmetry",","," leading"," to"," a"," lack"," of"," predic","tivity"," in"," string"," theory","."," We"," attempt"," to"," resolve"," this"," issue"," by"," exploring"," the"," interplay"," between"," these"," two"," symmetries"," on"," the"," heter","otic"," landscape","."," Our"," key"," idea"," is"," to"," consider"," the"," geometric"," and"," topological"," properties"," of"," Cal","abi","-","Y","au"," manifolds",","," which"," serve"," as"," the"," compac","tification"," spaces"," in"," heter","otic"," string"," theory","."," We"," utilize"," advanced"," computational"," methods",","," including"," algorithmic"," algebraic"," geometry"," and"," machine"," learning"," techniques",","," to"," probe"," the"," vast"," landscape"," of"," possible"," Cal","abi","-","Y","au"," compac","tifications","."," Our"," results"," indicate"," that"," supers","ymmetry"," and"," gauge"," symmetry"," are"," not"," independent"," notions",","," but"," rather"," are"," intertwined"," through"," their"," geometric"," and"," topological"," realiz","ations"," on"," the"," heter","otic"," landscape","."," We"," find"," that"," specific"," regions"," of"," the"," landscape",","," characterized"," by"," certain"," topological"," invariants",","," exhibit"," a"," higher"," propensity"," for"," supers","ymmetry"," and"," gauge"," symmetry"," to"," coexist","."," These"," findings"," have"," important"," implications"," for"," model"," building"," and"," phenomen","ology"," in"," string"," theory",","," and"," may"," ultimately"," shed"," light"," on"," the"," underlying"," structure"," of"," the"," universe","."],"sub_source":"arxiv","model":"llama3-70b","label":1}