{"text_id":166429,"tokens":["**","Nails"," and"," ninjas","."," **","\n\n","Floor","boards"," cre","ak"," when"," they"," loosen","."," The"," cre","aking"," sound"," is"," the"," nail"," that"," fast","ens"," the"," floor","board"," that"," you"," step"," on"," the"," the"," to"," the"," jo","ist"," slipping"," over"," the"," loose"," floor","board","."," ","\n\n","As"," floors"," age",","," when"," you"," step"," on"," the"," part"," that"," is"," not"," directly"," over"," a"," jo","ist",","," it"," causes"," the"," floor","board"," to"," flex",","," which"," pulls"," up"," on"," the"," nails","."," Over"," time"," this"," loos","ens"," up"," and"," the"," nail"," rubs"," on"," the"," board"," like"," fingernails"," on"," a"," chalkboard","."," ","\n\n","If"," you"," step"," slowly",","," you"," elongate"," the"," amount"," of"," time"," this"," cre","aking"," happens","."," ","\n\n","**","U","gu","is","ub","ari","**","\n\n","If"," you","'","ve"," ever"," been"," inside"," a"," traditional"," Japanese"," palace"," you"," might"," notice"," how"," cre","aky"," the"," floors"," are","."," ","\n\n","In"," feudal"," Japan",","," ninjas"," were"," often"," hired"," to"," assassin","ate"," rival"," war","lords"," and"," politicians","."," At"," one"," point",","," ninja"," attacks"," were"," such"," a"," problem",","," and"," so"," feared"," that"," samurai"," started"," building"," their"," castles"," with"," thin"," upward"," facing"," nails"," designed"," to"," cause"," floor","boards"," to"," cre","ak"," on"," on","purpose","."," ","\n\n","These"," cre","aky"," designed"," were"," called"," ugu","is","ub","ari"," or"," night","ingale"," floors"," and"," functioned"," as"," ancient"," intruder"," alarms"," for"," hundreds"," of"," years","."],"sub_source":"reddit","model":"human","label":0}