{"text_id":169476,"tokens":["."," The"," National"," Register"," of"," Historic"," Places"," listings"," in"," Sullivan"," County",","," Indiana",","," document"," the"," history"," of"," the"," county"," and"," its"," many"," structures",","," sites",","," and"," districts","."," Established"," in"," ","1","9","6","6",","," the"," National"," Register"," of"," Historic"," Places"," is"," the"," United"," States"," federal"," government","'","s"," official"," list"," of"," districts",","," sites",","," buildings",","," structures",","," and"," objects"," deemed"," worthy"," of"," preservation"," and"," recognition","."," The"," listings"," in"," Sullivan"," County",","," Indiana",","," include"," sites",","," buildings",","," structures",","," and"," objects"," located"," in"," the"," county","."," Sullivan"," County"," was"," organized"," in"," ","1","8","4","4",","," and"," many"," of"," the"," sites"," listed"," are"," associated"," with"," the"," earliest"," history"," of"," the"," county","."," These"," listings"," include"," places"," reflecting"," the"," diverse"," experiences"," of"," both"," rural"," and"," urban"," neighborhoods",","," from"," Indian"," mounds"," to"," the"," town"," square","."," Sullivan"," County"," also"," has"," rich"," railroad"," and"," agricultural"," history",","," and"," many"," sites"," associated"," with"," those"," industries"," are"," listed"," on"," the"," National"," Register"," as"," well","."," Of"," the"," ","3","5"," sites"," listed"," in"," Sullivan"," County",","," ","2","8"," are"," houses","."," These"," range"," from"," a"," Greek"," Revival"," farmhouse"," built"," in"," the"," ","1","8","4","0","s"," to"," a"," modern"," ranch"," built"," in"," the"," ","1","9","5","0","s","."," In"," addition"," to"," the"," houses",","," there"," are"," two"," churches",","," a"," cemetery",","," three"," barns",","," an"," office"," building",","," and"," a"," school","."," The"," listings"," also"," include"," cemeteries",","," Indian"," mounds",","," and"," the"," town"," square"," of"," Sullivan",","," the"," county"," seat","."," Of"," particular"," interest"," is"," the"," Patton"," School","house",","," built"," in"," ","1","8","8","4"," and"," listed"," in"," ","2","0","0","1","."," The"," school"," is"," an"," example"," of"," an"," one","-","room"," rural"," school","house",","," with"," its"," original"," wood"," frame"," construction",","," recessed"," door",","," and"," central"," chimney","."," Sullivan"," County","\u2019","s"," architectural"," heritage"," is"," also"," documented"," through"," its"," two"," historic"," districts","."," The"," Carlisle"," Home","place"," Historic"," District"," is"," one"," of"," the"," oldest"," districts"," in"," the"," state",","," dating"," back"," to"," the"," pre","-","Civil"," War"," era","."," It"," features"," a"," large"," collection"," of"," mid","-","nine","teenth"," century"," homes"," along"," the"," Wabash"," River","."," The"," Sharon","\u2019","s"," Corner"," Historic"," District"," preserves"," the"," history"," and"," architecture"," of"," a"," small"," community"," north"," of"," Sullivan","."," It"," features"," buildings"," from"," ","1","8","5","3"," to"," the"," present"," and"," showcases"," a"," variety"," of"," vernacular",","," Italian","ate",","," and"," Greek"," Revival","-","style"," buildings"," as"," well"," as"," many"," contributing"," out","buildings"," and"," historic"," elements","."," The"," National"," Register"," of"," Historic"," Places"," in"," Sullivan"," County"," provides"," an"," important"," way"," to"," understand"," the"," history"," of"," the"," county"," and"," its"," people","."," The"," listings"," recognize"," and"," commemorate"," the"," various"," experiences",","," contributions",","," and"," landscapes"," of"," this"," rural"," Indiana"," community","."],"sub_source":"wikipedia","model":"davinci","label":1}