{"text_id":187091,"tokens":["Best"," place"," in"," Charlotte"," for"," comics",","," hands"," down","."," Sadly",","," not"," the"," best"," place"," to"," go"," for"," a"," friendly"," staff","."," Cond","esc","ending"," tones"," and"," mockery"," of"," things"," I"," asked"," for","was"," inquiring"," about"," are"," not"," a"," good"," way"," to"," get"," return"," business","!:"," (","I","'","ll"," buy"," online"," before"," I"," go"," in"," here"," again","."],"sub_source":"yelp","model":"human","label":0}