{"text_id":194747,"tokens":["We"," extend"," the"," concepts"," of"," integrable"," and","lect"," Fran\u00e7a","-","P","omer","antz"," calendars",","," and"," the"," associated"," Witten"," diagrams",",","to"," the"," setting"," of"," non","-","commutative"," Lie"," groups","."," We"," show"," that","the"," Witten"," diagram"," of"," a"," non","-","commutative"," integrable"," calendar"," is"," symmetric",",","and"," that"," the"," symmetric"," Witten"," diagram"," of"," a"," calendar"," general","izes"," the","Wit","ten"," diagram"," of"," the"," Lie"," algebra"," of"," the"," underlying"," group","."," We"," show"," further","that"," a"," generalization"," of"," the"," theory"," of"," integrable"," calendars"," and"," Witten","di","agrams",","," developed"," by"," Donaldson"," and"," Thomas"," for"," the"," case"," of","commutative"," groups",","," can"," be"," obtained"," by"," considering"," the"," action"," of"," the"," sagging","graph"," on"," the"," symmetric"," Witten"," diagram","."," As"," an"," application",","," we"," show"," that","the"," symmetric"," Witten"," diagram"," of"," a"," non","-","commutative"," sub","variety"," of"," a"," Lie","g","rop","ens","ata"," is"," isomorphic"," to"," the"," total"," Witten"," diagram"," of"," the"," variety",","," and"," hence"," that","the"," symmetric"," Witten"," diagram"," is"," a"," generalization"," of"," the"," geometry"," of"," the","\"","ni","elsen"," structure","\""," of"," the"," variety","."," We"," show"," further"," that"," the"," symmetric","Wit","ten"," diagram"," of"," the"," quotient"," of"," a"," commutative"," sub","variety"," by"," a"," commutative"," Lie","group"," is"," a"," leaf",","," and"," that"," the"," symmetric"," Witten"," diagram"," of"," the"," quotient"," of","a"," non","-","commutative"," sub","variety"," by"," a"," non","-","commutative"," Lie"," group"," is"," a"," K","3","-","symmetric"," graph",","," called"," the"," con","if","old","."],"sub_source":"arxiv","model":"cohere","label":1}