{"text_id":199138,"tokens":["We"," develop"," a"," methodology"," for"," the"," calculation"," of"," surface"," free"," energies"," based","\n","on"," the"," probability"," distribution"," of"," a"," wandering"," interface","."," Using"," a"," simple","\n","extension"," of"," the"," N","pT"," sampling",","," we"," allow"," the"," interface"," area"," to"," randomly"," probe","\n","the"," available"," space"," and"," evaluate"," the"," surface"," free"," energy"," from"," histogram","\n","analysis"," and"," the"," corresponding"," average","."," The"," method"," is"," suitable"," for"," studying","\n","systems"," with"," either"," continuous"," or"," discontinuous"," potentials",","," as"," it"," does"," not","\n","require"," explicit"," evaluation"," of"," the"," vi","rial","."," The"," proposed"," algorithm"," is"," compared","\n","with"," known"," results"," for"," the"," surface"," tension"," of"," Lenn","ard","--","Jones"," and"," Square"," Well","\n","fluid",","," as"," well"," as"," for"," the"," interface"," tension"," of"," a"," bead","--","spring"," polymer"," model"," and","\n","good"," agreement"," is"," found","."," We"," also"," calculate"," interfacial"," tensions"," of"," freely","\n","jointed"," tangent"," hard"," sphere"," chains"," on"," a","thermal"," walls"," for"," a"," wide"," range"," of"," chain","\n","lengths"," and"," densities","."," The"," results"," are"," compared"," with"," three"," different","\n","theoretical"," approaches",","," Scal","ed"," Particle"," Theory",","," the"," Yu"," and"," Wu"," density","\n","functional"," theory"," and"," an"," analytical"," approximation"," based"," on"," the"," latter"," approach",".","\n","Whereas"," S","PT"," only"," yields"," qualitative"," results",","," the"," last"," two"," approaches"," are"," found","\n","to"," yield"," very"," good"," agreement"," with"," simulations","."],"sub_source":"arxiv","model":"human","label":0}