{"text_id":201110,"tokens":["Because"," they"," are"," so"," new",","," many"," people"," do"," not"," understand"," the"," major"," benefits"," and"," drawbacks"," of"," trampoline"," gyms","."," Make"," sure"," to"," consider"," that",":","\n","Jumping"," on"," tramp","ol","ines"," offers"," a"," low"," impact"," way"," to"," practice"," traditional"," exercises",".","\n","Tra","mp","oline"," gyms"," make"," seemingly"," tedious"," exercise"," fun",".","\n","Because"," of"," their"," costs",","," trampoline"," gyms"," may"," not"," be"," as"," accessible"," as"," regular"," types"," of"," gym",".","\n","The"," many"," age"," groups"," present"," at"," a"," trampoline"," gym"," creates"," an"," atmosphere"," that"," may"," create"," distractions"," for"," hardcore"," fitness"," gurus",".;","\n",","," As"," a"," fun"," way"," to"," exercise",","," a"," wide"," variety"," of"," people"," use"," trampoline"," gyms","."," Thus",","," trampoline"," gyms"," are"," a"," great"," way"," to"," transition"," people"," who"," are"," un","interested"," in"," exercise"," into"," an"," exercise"," routine","."," Some"," groups"," who"," may"," especially"," benefit"," from"," trampoline"," gyms"," include",":","\n","Children"," and"," teens",".","\n","College"," students",".","\n","Young"," professionals",".","\n","People"," with"," joint"," problems",".","\n","Elder","ly"," people"," who"," do"," not"," have"," bone"," problems","."," Elderly"," people"," suffering"," from"," osteoporosis"," should"," exercise"," caution"," when"," visiting"," trampoline"," gyms",".,"," Finding"," a"," trampoline"," gym"," might"," be"," difficult"," depending"," on"," your"," region","."," Thus",","," it"," may"," take"," you"," a"," little"," work"," to"," locate"," one"," that"," is"," convenient"," for"," you","."," To"," find"," a"," gym",":","\n","Search"," for"," one"," on"," the"," internet",".","\n","Use"," the"," Yellow"," Pages",".","\n","Ask"," friends"," or"," fitness"," experts"," you"," know",".","\n","Call"," local"," gyms"," to"," see"," if"," they"," have"," a"," section"," of"," their"," facilities"," dedicated"," to"," tramp","ol","ines",".,"," Ultimately",","," trampoline"," time"," should"," be"," just"," one"," part"," of"," your"," over"," all"," work"," out","."," While"," it"," offers"," great"," cardio"," and"," limited"," weight"," training",","," it"," may"," not"," provide"," everything"," you"," need"," to"," meet"," your"," fitness"," goals","."," By"," using"," it"," as"," supplement"," to"," other"," types"," of"," training",","," you","'","ll"," create"," an"," effective"," routine",".","\n","Schedule"," two"," visits"," a"," week"," to"," the"," trampoline"," gym","."," For"," instance",","," weight"," train"," at"," a"," regular"," gym"," on"," Monday",","," Wednesday",","," and"," Friday",","," bounce"," at"," a"," trampoline"," gym"," on"," Tuesday"," and"," Thursday",","," and"," run"," or"," walk"," on"," Saturday"," and"," Sunday",".","\n","Reserve"," simple"," cardio"," and"," aerobic"," exercises"," for"," the"," trampoline"," gym","."," For"," instance",","," save"," any"," impact"," related"," activity",","," like"," jumping"," jacks",","," for"," the"," trampoline"," gym",".","\n","Think"," about"," reserving"," simple"," weight"," training"," exercises"," like"," push","ups"," and"," sit","-","ups"," for"," the"," trampoline"," gym","."," This"," way"," you","\u2019","ll"," be"," able"," to"," perform"," these"," exercises"," in"," a"," low","-","impact"," environment",".,"," The"," basic"," bounce"," is"," perhaps"," the"," centerpiece"," of"," a"," trampoline"," workout","."," While"," it"," is"," relatively"," simple",","," it"," also"," burns"," substantial"," calories"," and"," will"," help"," improve"," your"," cardio"," with"," little"," effort","."," To"," do"," a"," basic"," bounce",":","\n","Get"," on"," the"," trampoline"," (","any"," size",").","\n","Position"," your"," feet"," about"," ","6"," inches"," (","1","5"," cm",")"," apart",".","\n","Make"," sure"," your"," arms"," are"," bent"," and"," your"," elbows"," are"," at"," your"," sides",".","\n","Bend"," your"," knees"," slightly",".","\n","Jump"," lightly","."," You"," should"," move"," about"," ","6"," inches"," (","1","5"," cm",")"," into"," the"," air",".","\n","Complete"," at"," least"," ","3","0"," repetitions",".,"," Tramp","oline"," leg"," lifts"," are"," similar"," to"," regular"," leg"," lifts"," but"," reduce"," the"," amount"," of"," stress"," and"," impact"," on"," your"," joints","."," They"," also"," enable"," you"," to"," stretch"," your"," muscles"," better","."," To"," do"," a"," trampoline"," leg"," lift",":","\n","Sit"," on"," the"," trampoline",".","\n","Lift"," your"," legs"," off"," the"," ground",".","\n","Tight","en"," and"," contract"," your"," abs",".","\n","Hold"," your"," contractions"," for"," ","2","0"," seconds",".","\n","Release"," your"," contractions",".","\n","Repeat"," your"," lifts"," and"," contractions"," ","3"," times",".,"," The"," power"," bounce"," with"," lateral"," reach"," works"," out"," not"," just"," your"," lower"," body",","," but"," also"," helps"," work"," out"," and"," stretch"," your"," arms"," and"," shoulders","."," To"," complete"," a"," power"," bounce"," with"," lateral"," reach",":","\n","Sit"," on"," the"," trampoline",".","\n","Quickly"," stand"," up"," and"," bounce",".","\n","Reach"," one"," arm"," across"," your"," body","."," Alternate"," your"," arms"," every"," bounce",".","\n","Return"," to"," sitting",".","\n","Repeat"," the"," sit",","," stand",","," reach",","," and"," bounce"," ","3","0"," times",".,"," Just"," as"," push","ups"," are"," an"," important"," part"," of"," a"," regular"," workout",","," they"," are"," also"," very"," important"," in"," a"," trampoline","-","based"," workout","."," Tramp","oline"," push","ups"," are"," a"," great"," low","-","impact"," activity"," that"," will"," help"," you"," improve"," your"," upper"," body"," strength",".","\n","Use"," a"," ","3"," or"," ","4"," foot"," trampoline"," (.","9"," meters"," to"," ","1",".","2"," meters",")","\n","Position"," your"," feet"," on"," the"," ground",".","\n","Plan","k"," your"," body"," upward"," and"," position"," your"," hands"," on"," the"," trampoline",".","\n","Push"," up"," and"," come"," back"," down"," ","1","0"," times",".,"," One"," of"," the"," biggest"," dangers"," to"," individual"," safety"," at"," trampoline"," gyms"," are"," multiple"," jumpers"," on"," one"," surface","."," As"," a"," result",","," you"," need"," to"," make"," sure"," you"," never"," jump"," on"," a"," surface"," where"," someone"," is"," already"," jumping",".","\n","If"," someone"," begins"," jumping"," on"," your"," surface",","," you"," should"," stop"," immediately"," and"," exit"," the"," surface",".","\n","Inform"," anyone"," who"," wants"," to"," jump"," with"," you"," that"," it"," is"," a"," safety"," hazard",".,"," Jumping"," without"," properly"," inspecting"," a"," trampoline"," is"," one"," of"," the"," biggest"," safety"," failures"," you"," can"," make"," at"," a"," trampoline"," gym","."," Because"," of"," this",","," you"," should"," use"," extreme"," care"," and"," look"," at"," a"," trampoline"," before"," using"," it",".","\n","Make"," a"," quick"," visual"," inspection"," of"," your"," trampoline","."," Make"," sure"," there"," are"," no"," tears",","," rips",","," or"," other"," visible"," problems",".","\n","Make"," sure"," no"," other"," exercise"," equipment"," is"," under"," or"," directly"," next"," to"," the"," trampoline",".","\n","Make"," sure"," no"," one"," else"," is"," getting"," ready"," to"," jump"," on"," the"," same"," trampoline",".,"," While"," there"," are"," several"," universal"," rules"," that"," most"," all"," gyms"," will"," adhere"," to",","," you"," need"," to"," make"," sure"," to"," thoroughly"," read"," gym"," specific"," rules",".","\n","Take"," note"," of"," posted"," rules"," when"," entering"],"sub_source":"wikihow","model":"human","label":0}