{"text_id":204525,"tokens":["This"," paper"," addresses"," the"," problem"," of"," how"," to"," improve"," the"," performance"," of"," multi","-","task"," reinforcement"," learning"," agents","."," The"," authors"," present"," a"," novel"," approach",","," Modular"," Multi","task"," Reinforcement"," Learning"," with"," Policy"," Sketches"," (","MM","RL","PS","),"," which"," utilizes"," a"," set"," of"," policy"," sketches"," to"," increase"," the"," agent","'","s"," ability"," to"," learn"," multiple"," tasks"," simultaneously",".","\n\n","Strengths",":","\n","-"," The"," authors"," provide"," a"," comprehensive"," overview"," of"," the"," current"," state"," of"," the"," art"," in"," multi","-","task"," reinforcement"," learning"," and"," discuss"," the"," challenges"," associated"," with"," it",".","\n","-"," The"," proposed"," approach",","," MM","RL","PS",","," is"," well","-","explained"," and"," the"," authors"," discuss"," the"," advantages"," of"," using"," policy"," sketches"," to"," improve"," multi","-","task"," reinforcement"," learning"," performance",".","\n","-"," The"," authors"," present"," empirical"," results"," to"," support"," the"," efficacy"," of"," their"," proposed"," approach",".","\n\n","Weaknesses",":","\n","-"," The"," paper"," does"," not"," provide"," a"," comparison"," of"," MM","RL","PS"," to"," other"," multi","-","task"," reinforcement"," learning"," techniques",".","\n","-"," The"," authors"," do"," not"," discuss"," the"," scalability"," of"," the"," proposed"," approach"," or"," how"," it"," could"," be"," applied"," to"," more"," complex"," tasks",".","\n","-"," The"," paper"," does"," not"," provide"," any"," insight"," into"," how"," the"," policy"," sketches"," are"," generated"," or"," how"," they"," are"," used"," to"," improve"," learning"," performance","."],"sub_source":"peerread","model":"davinci","label":1}