{"text_id":211003,"tokens":["Caffeine"," content"," in"," them",","," which"," can"," be"," harmful"," to"," your"," health"," if"," consumed"," too"," much"," and"," regularly"," over"," time","."," Caffeine"," has"," been"," shown"," to"," increase"," blood"," pressure"," levels"," as"," well"," as"," heart"," rate"," when"," taken"," in"," excess"," amounts","."," Energy"," drinks"," are"," also"," high"," in"," sugar"," (","which"," contributes"," to"," obesity",")"," and"," other"," artificial"," ingredients"," that"," may"," cause"," allergic"," reactions"," or"," even"," lead"," to"," liver"," damage","."," The"," caffeine"," contained"," within"," these"," products"," will"," not"," have"," any"," effect"," on"," someone"," who"," does"," not"," drink"," it"," often"," enough"," because"," they"," do"," not"," build"," up"," tolerance"," like"," people"," with"," regular"," consumption"," habits"," would"," develop","."," This"," means"," that"," one"," cup"," per"," day"," should"," be"," fine"," but"," anything"," more"," than"," this"," could"," potentially"," harm"," their"," body","'","s"," ability"," to"," function"," properly","."," Coffee"," contains"," less"," caffeine"," then"," an"," average"," energy"," drink","."," It"," is"," possible"," to"," consume"," large"," quantities"," of"," coffee"," without"," experiencing"," negative"," side"," effects"," from"," its"," use"," since"," most"," individuals"," already"," tolerate"," some"," amount"," of"," caffeine"," through"," normal"," daily"," activities"," such"," as"," eating"," chocolate"," bars"," etc"],"sub_source":"reddit","model":"bloomz","label":1}