{"text_id":213919,"tokens":["While"," still"," a"," student",","," he"," was"," offered"," a"," small"," unpaid"," intern"," job"," at"," Universal"," Studios"," with"," the"," editing"," department","."," He"," was"," later"," given"," the"," opportunity"," to"," make"," a"," short"," film"," for"," theatrical"," release",","," the"," ","2","6","-","minute",","," ","3","5","mm",","," Amb","lin","',"," which"," he"," wrote"," and"," directed","."," Studio"," vice"," president"," Sidney"," She","in","berg"," was"," impressed"," by"," the"," film",","," which"," had"," won"," a"," number"," of"," awards",","," and"," offered"," Spielberg"," a"," seven","-","year"," directing"," contract","."," It"," made"," him"," the"," youngest"," director"," ever"," to"," be"," signed"," for"," a"," long","-","term"," deal"," with"," a"," major"," Hollywood"," studio",".:","5","4","8"," He"," subsequently"," dropped"," out"," of"," college"," to"," begin"," professionally"," directing"," TV"," productions"," with"," Universal","."],"sub_source":"squad","model":"human","label":0}