{"text_id":221398,"tokens":["Let"," $","G","$"," be"," a"," simple"," and"," simply"," connected"," algebraic"," group"," over"," an","\n","algebra","ically"," closed"," field"," $\\","Bbb","k","$"," of"," characteristic"," $","p",">","0","$."," Assume"," that"," $","p","$"," is","\n","good"," for"," the"," root"," system"," of"," $","G","$"," and"," that"," the"," covering"," map"," $","G","_{","sc","}"," \\","rightarrow","\n","G","$"," is"," separable","."," In"," previous"," work"," we"," proved"," the"," existence"," of"," a"," (","not"," necessarily","\n","unique",")"," Springer"," isomorphism"," for"," $","G","$"," that"," behaved"," like"," the"," exponential"," map"," on","\n","the"," res","tic","ted"," null","cone"," of"," $","G","$.","\n","  ","In"," the"," present"," paper"," we"," give"," a"," formal"," definition"," of"," these"," maps",","," which"," we"," call","\n","general","ized"," exponential"," maps",".'"," We"," provide"," an"," explicit"," and"," uniform"," construction","\n","of"," such"," maps"," for"," all"," root"," systems",","," demonstrate"," their"," existence"," over","\n","$\\","mathbb","{","Z","}_{(","p",")}$,"," and"," give"," a"," complete"," parameter","ization"," of"," all"," such"," maps","."," One","\n","application"," is"," that"," this"," gives"," a"," uniform"," approach"," to"," dealing"," with"," the","\n","\"","saturation"," problem","\""," for"," a"," un","ip","otent"," element"," $","u","$"," in"," $","G","$,"," providing"," a"," new"," proof","\n","of"," the"," known"," result"," that"," $","u","$"," lies"," inside"," a"," subgroup"," of"," $","C","_","G","(","u",")$"," that"," is","\n","is","omorphic"," to"," a"," truncated"," Witt"," group","."," We"," also"," develop"," a"," number"," of"," other","\n","explicit"," and"," new"," computations"," for"," $\\","mathfrak","{","g","}$"," and"," for"," $","G","$."," This"," paper"," grew","\n","out"," of"," an"," attempt"," to"," answer"," a"," series"," of"," questions"," posed"," to"," us"," by"," P","."," De","ligne",",","\n","who"," also"," contributed"," several"," of"," the"," new"," ideas"," that"," appear"," here","."],"sub_source":"arxiv","model":"human","label":0}