{"text_id":226558,"tokens":["Twitter","'","s"," board"," intends"," to"," enforce"," Elon"," Musk","'","s"," merger"," agreement","."," Musk"," had"," agreed"," to"," a"," transaction"," at"," ","5","4",".","2","0"," per"," share",","," but"," put"," the"," deal"," on"," hold"," pending"," proof"," that"," less"," than"," ","1","0"," of"," the"," company","'","s"," shares"," were"," held"," by"," short"," sellers",","," as"," required"," by"," the"," deal","'","s"," merger"," agreement","."," However",","," a"," Bloomberg"," report"," on"," Wednesday"," said"," that"," Twitter"," found"," that"," short"," sellers"," owned"," more"," than"," ","1","0"," of"," the"," company","'","s"," shares",","," triggering"," a"," requirement"," that"," the"," company"," provide"," Musk"," with"," additional"," information","."," Twitter"," has"," yet"," to"," comment"," on"," the"," report","."," Short"," sellers"," sell"," borrowed"," shares"," in"," a"," company"," and"," later"," buy"," them"," back"," at"," a"," lower"," price",","," hoping"," to"," make"," a"," profit"," by"," betting"," on"," a"," fall"," in"," the"," stock"," price","."," The"," report"," said"," that"," Musk"," could"," seek"," a"," modification"," of"," the"," merger"," agreement"," or"," walk"," away"," from"," the"," deal"," altogether","."," Twitter","'","s"," stock"," is"," down"," ","1","3"," in"," ","2","0","1","8","."," Tesla","'","s"," shares"," have"," fallen"," ","4","1"," in"," the"," same"," period","."],"sub_source":"tldr","model":"GLM130B","label":1}