{"text_id":239502,"tokens":["Jeff"," Salmon"," (","b","."," ","1","9","7","7",")"," is"," an"," English"," actor","."," He"," studied"," at"," the"," London"," Academy"," of"," Music"," and"," Dramatic"," Art"," and"," is"," a"," former"," member"," of"," the"," National"," Youth"," Theater","."," He"," made"," his"," acting"," debut"," in"," the"," ","2","0","0","1"," British"," television"," series"," Mother","Love","."," Since"," then",","," his"," roles"," have"," included"," Daniel"," in"," the"," Sky"," One"," TV"," series",","," Drop"," Dead"," Gorgeous"," (","US"," title",":"," A"," Chance"," to"," Feel"," Big","),"," Joe"," in"," the"," British"," science"," fiction"," series"," Blink",","," Zed"," in"," the"," British"," drama"," The"," Driver",":"," See"," Your"," Future"," with"," Boxing",","," and"," Heist"," Society","'","s"," criminal"," mastermind"," Lord"," plays"," Jia","."," His"," most"," famous"," role"," is"," that"," of"," Scott"," Marshall"," on"," the"," British"," Channel"," ","4"," comedy","-","drama",","," Mis","fits",","," for"," which"," he"," was"," nominated"," for"," a"," Best"," Actor"," Baf","ta","."," exploit"," \"","Jeff"," Salmon","\""," is"," an"," English"," actor","."," He"," studied"," at"," the"," London"," Academy"," of"," Music"," and"," Dramatic"," Art"," and"," is"," a"," former"," member"," of"," the"," National"," Youth"," Theater","."," He"," made"," his"," acting"," debut"," in"," the"," ","2","0","0","1"," British"," television"," series"," Mother","Love","."," Since"," then",","," his"," roles"," have"," included"," Daniel"," in"," the"," Sky"," One"," TV"," series",","," Drop"," Dead"," Gorgeous"," (","US"," title",":"," A"," Chance"," to"," Feel"," Big","),"," Joe"," in"," the"," British"," science"," fiction"," series"," Blink",","," Zed"," in"," the"," British"," drama"," The"," Driver",":"," See"," Your"," Future"," with"," Boxing",","," and"," Heist"," Society","'","s"," criminal"," mastermind"," Lord"," wonder"," Biographical"," details"," Acting"," debut"," ","2","0","0","1",":"," Mother","Love"," Drop"," Dead"," Gorgeous"," (","2","0","0","1",")"," Sky"," One"," TV"," series"," Blink"," The"," Driver",":"," See"," Your"," Future"," with"," Boxing"," Zed"," Mis","fits"," (","2","0","1","5",")"," Award"," nominations"," Best"," Actor"," Baf","ta"," Reference",":"," https","://","en",".","wikipedia",".","org","/","wiki","/","Jeff","_","Salmon"],"sub_source":"wikipedia","model":"dolly","label":1}