{"text_id":246160,"tokens":["There"," are"," tons"," of"," free"," streaming"," porn"," sites"," on"," the"," internet"," because"," that"," is"," what"," the"," internet"," is"," full"," of","."," Granted",","," porn"," did"," not"," make"," the"," technology"," that"," allows"," you"," to"," see"," free",","," HD"," quality",","," streaming",","," graphic"," lesbian"," chat"," rooms",","," but"," porn"," gave"," a"," use"," for"," the"," high"," quality"," pornography"," you"," see"," on"," the"," internet","."," ","\n","Gambling"," websites",","," the"," second"," most"," common"," reason"," people"," go"," on"," the"," internet",","," is"," a"," distant"," second","."," The"," porn"," websites"," bring"," you"," what"," you"," want"," by"," providing"," an"," application"," for"," the"," latest"," and"," greatest"," uses"," for"," the"," internet","."," ","\n","Take"," adult"," oriented"," chat"," rooms","."," There"," was"," the"," technology"," there"," for"," the"," chat"," rooms",","," but"," someone"," came"," up"," with"," the"," idea"," to"," get"," faster"," responses"," by"," having"," the"," chats"," in"," real"," time","."," The"," porn"," site"," tells"," the"," domain"," host"," that"," they"," will"," only"," register"," with"," that"," domain"," host"," if"," they"," can"," guarantee"," that"," ","5","0","%"," of"," the"," traffic"," will"," be"," broadband","."," The"," domain"," host"," agrees"," and"," tells"," the"," ISP","'","s"," that"," they"," will"," only"," allow"," traffic"," from"," the"," ISP"," if"," they"," can"," get"," ","7","5","%"," broadband"," traffic","."," The"," ISP"," begins"," a"," massive"," campaign"," to"," get"," broadband"," subscribers","."," ","\n","If"," enough"," traffic"," goes"," through"," the"," ISP"," for"," broadband",","," much"," of"," that"," will"," go"," to"," the"," domain"," host","."," The"," ISP"," will"," be"," able"," to"," lower"," its"," rates"," for"," broadband"," traffic"," because"," of"," all"," the"," new"," subscribers","."," ","\n","The"," domain"," host"," realizes"," they"," have"," a"," cash"," cow"," when"," they"," see"," all"," the"," traffic"," the"," porn"," site"," is"," getting","."," The"," domain"," host"," gives"," cash"," to"," the"," website"," since"," the"," domain"," host"," is"," seeing"," a"," ton"," more"," traffic","."," All"," the"," site"," has"," to"," do"," is"," keep"," drawing"," more"," traffic"," to"," the"," domain"," host","."," Keep"," this"," up"," until"," you"," get"," Dan","ica"," Patrick"," naked"," in"," a"," bunch"," of"," TV"," commercials"," and"," then"," you"," get"," people"," wanting"," to"," register"," with"," the"," same"," domain"," host"," that"," brought"," you"," red","Tube","."," Those"," people"," pay"," for"," their"," websites","."," You","Porn"," gets"," paid"," for"," being"," on"," the"," domain"," host","."],"sub_source":"reddit","model":"human","label":0}