{"text_id":255999,"tokens":["Un"," petit"," cafe"," tres"," sympa"," qui"," fait"," aussi"," showroom",","," l","'","ambiance"," est"," de","contra","c","tee",","," le"," menu"," est"," simple"," mais"," efficace",","," les"," prix"," sont"," plu","tot"," bas"," pour"," le"," quartier",","," le"," service"," est"," cool"," et"," sympa","."," Cela"," change"," de"," certains"," cafes"," branches"," hors"," de"," prix"," et"," qui"," ont"," tendance"," a"," vous"," prendre"," un"," peu"," de"," haut"," parfois","."," Petit"," plus",":"," une"," jolie"," terrasse"," a"," l","'","arri","ere"," qui"," permet"," de"," faire"," une"," pause"," hors"," de"," l","'","ag","itation","!"],"sub_source":"yelp","model":"human","label":0}