{"text_id":30221,"tokens":["Harvard"," is"," a"," large",","," highly"," residential"," research"," university","."," The"," nominal"," cost"," of"," attendance"," is"," high",","," but"," the"," University","'","s"," large"," endowment"," allows"," it"," to"," offer"," generous"," financial"," aid"," packages","."," It"," operates"," in"," Cambridge",","," Massachusetts",","," and"," its"," undergraduate"," school"," offers"," degrees"," at"," seven"," levels"," (","A","-","G",")"," from"," both"," liberal"," arts"," and"," professional"," backgrounds","."," The"," Harvard"," Gazette"," is"," the"," official"," student"," newspaper",";"," as"," such"," it"," contains"," articles"," written"," by"," students"," about"," topics"," which"," include"," current"," events","."," This"," section",","," called"," \"","Undergraduate"," Perspectives",",\""," features"," commentary"," on"," issues"," concerning"," campus"," community"," life","."," Students"," are"," invited"," to"," submit"," short"," pieces"," for"," publication","."],"sub_source":"squad","model":"opt_iml_30b","label":1}