{"text_id":31627,"tokens":["We"," investigate"," the"," phenomenon"," of"," gauge","-","Higgs"," unification"," and"," radiative"," elect","row","eak"," symmetry"," breaking"," in"," the"," context"," of"," warped"," extra"," dimensions","."," Motiv","ated"," by"," the"," desire"," to"," address"," the"," hierarchy"," problem"," and"," the"," lack"," of"," a"," natural"," explanation"," for"," the"," Higgs"," mass"," in"," the"," Standard"," Model",","," we"," explore"," the"," possibility"," of"," realizing"," elect","row","eak"," symmetry"," breaking"," through"," a"," dynamical"," mechanism","."," In"," this"," framework",","," the"," Higgs"," boson"," emerges"," as"," a"," composite"," state"," of"," the"," extra","-","dimensional"," gauge"," field",","," providing"," a"," natural"," explanation"," for"," its"," mass","."," We"," employ"," a"," five","-","dimensional"," warped"," space","-","time"," geometry",","," which"," generates"," a"," natural"," hierarchy"," between"," the"," elect","row","eak"," scale"," and"," the"," cutoff"," scale"," of"," the"," theory","."," Our"," analysis"," reveals"," that"," radiative"," corrections",","," driven"," by"," the"," bulk"," gauge"," and"," ferm","ion"," fields",","," trigger"," elect","row","eak"," symmetry"," breaking",","," dynamically"," generating"," the"," required"," vacuum"," expectation"," value"," of"," the"," Higgs"," field","."," We"," obtain"," a"," set"," of"," predictive"," relations"," between"," the"," elect","row","eak"," scale",","," the"," Higgs"," mass",","," and"," the"," compac","tification"," scale",","," providing"," a"," smoking"," gun"," signature"," for"," this"," scenario","."," Our"," results"," offer"," a"," compelling"," alternative"," to"," traditional"," approaches"," to"," elect","row","eak"," symmetry"," breaking",","," highlighting"," the"," potential"," of"," gauge","-","Higgs"," unification"," in"," warped"," extra"," dimensions"," to"," elucidate"," the"," fundamental"," laws"," of"," nature","."],"sub_source":"arxiv","model":"llama3-70b","label":1}