{"text_id":38265,"tokens":["Begin"," summary"," Subjects",":"," ","9","8","3","4"," and"," ","0","3","3","1"," ALERT","!"," Sus","picious"," activity"," flag"," ","3","0","1","-","1","4"," Location",".","flag"," Central"," Park"," Text",".","flag"," {"," fire"," (","1",");"," explode"," (","1",");"," burning"," (","2",");"," torture"," (","2",");"," kill"," (","2",")"," }"," End"," summary"," SMS"," tracking"," begin",":"," Date"," :"," I"," made"," it"," out","."," Fucking"," prison","."," ","0","3","3","1",":"," Oh"," sweet","."," ","9","8","3","4",":"," Need"," to"," meet","."," Burning"," for"," u","."," ","0","3","3","1",":"," Don","'","t"," have"," much"," time","."," ","9","8","3","4",":"," I","'","ll"," take"," what"," I"," can"," get","."," Being"," this"," far"," from"," u"," is"," torture","."," ","0","3","3","1",":"," Central"," Park","?"," ","9","8","3","4",":"," ","1","5"," min"," ","9","8","3","4",":"," God"," I"," needed"," that"," ","0","3","3","1",":"," We"," didn","'","t"," even"," do"," any","thin"," lol"," ","9","8","3","4",":"," I"," held"," u"," thats"," enough"," ","0","3","3","1",":"," A","we"," ","9","8","3","4",":"," Got"," ta"," sneak"," back"," in"," b","4"," warden"," wake","z"," up",","," love"," u"," ","0","3","3","1",":"," ilu","2"," Date"," :"," u"," up","?"," ","0","3","3","1",":"," Just"," ","4"," a"," bit"," whats"," up"," ","9","8","3","4",":"," Think","in"," bout"," u"," ","0","3","3","1",":"," o","?"," ","9","8","3","4",":"," bout"," ur"," ass"," m","mmmm","mmmm"," ","0","3","3","1",":"," lol"," shut","up"," ","9","8","3","4",":"," wan"," na"," slap"," it"," a"," bit"," ","0","3","3","1",":"," mm"," yeah","?"," ","9","8","3","4",":"," And"," squeeze"," while"," I"," kiss"," u"," ","0","3","3","1",":"," mm"," yeah"," dont"," stop"," ","9","8","3","4",":"," kiss"," u"," till"," u"," melt"," ","0","3","3","1",":"," im"," melting"," now"," take"," me"," ","9","8","3","4",":"," slide"," ur"," pants"," off"," and"," get"," inside"," u"," ","0","3","3","1",":"," mmm"," yeah"," right"," there"," ","9","8","3","4",":"," faster"," and"," faster"," ","0","3","3","1",":"," Yeah"," give"," it"," to"," me"," ","9","8","3","4",":"," explode"," in"," u"," ","0","3","3","1",":"," I","'","m"," on"," fire"," ","4"," u"," ","9","8","3","4",":"," Feel"," u"," so"," hot"," ","0","3","3","1",":"," ilu"," ","9","8","3","4",":"," nite"," baby"," ilu","2"," Date"," :"," miss"," u"," ","9","8","3","4",":"," miss"," u"," ","2",","," can"," I"," c"," u","?"," ","0","3","3","1",":"," not"," ","2","nite"," s","ry"," b","by"," ","9","8","3","4",":"," torture"," ","0","3","3","1",":"," I"," no"," b","by"," but"," someday"," it","ll"," be"," better"," ","9","8","3","4",":"," Just"," got"," ta"," get"," outta"," here"," ","0","3","3","1",":"," I"," no"," ","9","8","3","4",":"," Burning"," for"," you"," b","by"," ","0","3","3","1",":"," T","mr","w"," maybe","?"," ","9","8","3","4",":"," I"," hope"," so",","," I","'","ll"," let"," u"," no"," ","0","3","3","1",":"," ok"," luv"," u"," ","9","8","3","4",":"," ilu","2"," Date"," :"," Central"," park",","," now"," ","0","3","3","1",":"," u"," ok","?"," ","9","8","3","4",":"," We"," need"," to"," talk"," ","0","3","3","1",":"," Fuck"," ok"," om","w"," ","0","3","3","1",":"," Fuck"," u","."," How"," c","ld"," u"," ","9","8","3","4",":"," S","ry"," ","0","3","3","1",":"," Dont"," tell"," me"," sorry"," fucker"," u"," owe"," me"," better"," I"," deserve"," better"," u"," asshole"," ","9","8","3","4",":"," I"," no"," Im"," s","ry"," ","0","3","3","1",":"," Fuck"," u"," I"," hope"," u"," die",","," I"," should"," kill"," u"," myself"," ","9","8","3","4",":"," I"," should"," kill"," myself"," ","1","st"," ","0","3","3","1",":"," u"," should"," u"," deserve"," to"," die"," broke"," my"," heart"," fuck"," u"," goodbye"," asshole"," SMS"," tracking"," end","."],"sub_source":"wp","model":"human","label":0}