{"text_id":58044,"tokens":["She"," had"," always"," been"," a"," shy"," girl",","," content"," to"," fly"," under"," the"," radar"," and"," stay"," out"," of"," the"," limelight","."," So"," when"," she"," received"," the"," invitation"," to"," the"," exclusive"," gala",","," she"," was"," stunned","."," Could"," that"," really"," be"," her","?"," She"," couldn","'","t"," believe"," it","!"," Excited","ly",","," she"," bust","led"," around"," picking"," out"," the"," perfect"," dress"," and"," shoes",","," and"," agonizing"," over"," the"," right"," hairstyle","."," After"," hours"," of"," preparation",","," she"," stepped"," in"," front"," of"," the"," mirror",","," taking"," in"," her"," reflection"," with"," a"," sense"," of"," pride","."," She"," had"," done"," it"," -"," she"," was"," ready"," to"," go","."," The"," night"," of"," the"," gala"," was"," like"," something"," straight"," out"," of"," a"," dream","."," She"," was"," surrounded"," by"," elegance"," and"," luxury"," as"," she"," mingled"," with"," people"," she"," had"," only"," seen"," in"," magazines","."," Everyone"," seemed"," so"," important",","," and"," yet"," here"," she"," was",","," standing"," among"," them","."," As"," she"," made"," her"," way"," across"," the"," room",","," she"," felt"," a"," newfound"," confidence"," swell"," inside"," her","."," She"," realized"," that"," if"," she"," could"," make"," it"," here",","," she"," could"," make"," it"," anywhere","."," Could"," that"," really"," be"," her","?"," Yes",","," indeed"," it"," could","."],"sub_source":"roct","model":"text-davinci-003","label":1}