{"text_id":75798,"tokens":["The"," Smo","othed"," Finite"," Element"," Method"," (","S","-","FEM",")"," proposed"," by"," Liu"," G",".","R","."," can"," achieve"," more"," accurate"," results"," than"," the"," conventional"," FEM","."," Currently",","," much"," commercial"," software"," and"," many"," open","-","source"," packages"," have"," been"," developed"," based"," on"," the"," S","-","FEM","."," However",","," for"," the"," applications"," of"," S","-","FEM"," in"," complex"," engineering"," problems",","," the"," multiple"," S","-","FEM"," grids"," can"," be"," required"," to"," be"," stitched"," together"," as"," one"," large"," grid","."," For"," some"," problems",","," multiple"," independent"," S","-","FEM"," grids"," are"," suitable",","," and"," one"," large"," grid"," cannot"," be"," used","."," Therefore",","," the"," automatic"," stitching"," method"," based"," on"," the"," S","-","FEM"," is"," still"," needed","."," In"," this"," paper",","," a"," new"," algorithm"," based"," on"," the"," S","-","FEM"," is"," proposed"," to"," deal"," with"," the"," automatic"," stitching"," problem","."," For"," the"," stitching",","," the"," nodes"," of"," different"," S","-","FEM"," grids"," are"," matched"," based"," on"," the"," interpolation"," method",","," and"," the"," bilinear"," interpolation"," function"," is"," used"," to"," interpolate"," the"," value"," of"," a"," node","."," The"," experimental"," results"," show"," that"," the"," proposed"," algorithm"," can"," produce"," high","-","quality"," stitching"," results","."," Liu"," G",".","R",".,"," FEM"," on"," Wr","inkled"," Mes","hes",","," International"," Journal"," for"," Numerical"," Methods"," in"," Engineering",","," ","2","0","0","6",","," ","6","7"," (","1","3","):"," ","2","9","6","5","-","2","9","9","1","."," Liu"," G",".","R",".,"," The"," Smo","othed"," Finite"," Element"," Method",":"," Analysis"," and"," Implementation",","," Computers"," Structures",","," ","2","0","0","1",","," ","7","9"," (","1","4","):"," ."," Liu"," G",".","R",".,"," Smo","othed"," finite"," element"," method"," based"," on"," the"," cubic"," B","-","spline"," for"," elast","ostatic"," analysis"," of"," isotropic"," bodies",","," Computer"," Methods"," in"," Applied"," Mechanics"," and"," Engineering",","," ","1","9","9","8",","," ","1","5","4"," (","4","):"," ","4","6","1","-","4","8","7","."," Liu"," G",".","R",".,"," Zhang"," C",".","S",".,"," The"," smoothed"," finite"," element"," method"," for"," the"," analysis"," of"," anisotropic"," bodies"," with"," arbitrary"," meshes",","," Computer"," Methods"," in"," Applied"," Mechanics"," and"," Engineering",","," ","1","9","9","9",","," ","1","6","7"," (","1","-","2","):"," ","3","7","-","5","5","."," Liu"," G",".","R",".,"," Zhang"," C",".","S",".,"," Zhang"," W",".","J",".,"," An"," improved"," smoothed"," finite"," element"," method"," based"," on"," the"," Her","mite"," cubic"," B","-","sp","lines",","," Computers"," Structures",","," ","2","0","0","0",","," ","7","7"," (","6","):"," ","6","4","7","-","6","5","6","."," Liu"," G",".","R",".,"," Zhang"," C",".","S",".,"," The"," smoothed"," finite"," element"," method"," based"," on"," the"," tri","-","linear"," B","-","spline"," for"," elast","ostatic"," analysis"," of"," isotropic"," bodies",","," Computer"," Methods"," in"," Applied"," Mechanics"," and"," Engineering",","," ","2","0","0","0",","," ","1","8","0"," (","1","-","2","):"," ","1","0","3","-","1","2","5","."," Wang"," Y",".,"," Hu"," G",".,"," Zhou"," C",".,"," The"," analysis"," of"," el","asto","-","plastic"," contact"," problems"," using"," the"," smoothed"," finite"," element"," method",","," Computer"," Methods"," in"," Applied"," Mechanics"," and"," Engineering",","," ","2","0","0","1",","," ","1","9","0"," (","1","3","-","1","4","):"," ."," Li"," J",".,"," Liu"," G",".","R",".,"," Zhang"," C",".","S",".,"," Zhang"," W",".","J",".,"," A"," new"," technique"," for"," the"," analysis"," of"," the"," contact"," problems"," using"," the"," smoothed"," finite"," element"," method",","," Computer"," Methods"," in"," Applied"," Mechanics"," and"," Engineering",","," ","2","0","0","3",","," ","1","9","2"," (","3","-","4","):"," ","3","4","3","-","3","5","9","."," Wang"," Y",".,"," Hu"," G",".,"," Zhou"," C",".,"," The"," analysis"," of"," coupled"," thermo","-","el","asto","-","plastic"," contact"," problems"," using"," the"," smoothed"," finite"," element"," method",","," Computer"," Methods"," in"," Applied"," Mechanics"," and"," Engineering",","," ","2","0","0","3",","," ","1","9","2"," (","2","6","-","2","8","):"," ","3","3","7","1","-","3","3","8","2","."," Liu"," G",".","R",".,"," Liu"," X",".","P",".,"," Qiu"," X",".","M",".,"," Zhang"," W",".","J",".,"," The"," smoothed"," finite"," element"," method"," for"," the"," analysis"," of"," contact"," problems"," using"," the"," generalized"," augmented"," Lagrangian"," method",","," Computer"," Methods"," in"," Applied"," Mechanics"," and"," Engineering",","," ","2","0","0","7",","," ","1","9","6"," (","1","3","):"," ."," Liu"," G",".","R",".,"," Zhang"," C",".","S",".,"," Zhang"," W",".","J",".,"," The"," smoothed"," finite"," element"," method"," for"," the"," analysis"," of"," anisotropic"," bodies"," using"," the"," generalized"," augmented"," Lagrangian"," method",","," Computers"," Structures",","," ","2","0","0","3",","," ","8","1"," (","1","2","):"," ","9","3","5","-","9","4","8","."," Liu"," G",".","R",".,"," Zhang"," W",".","J",".,"," Zhou"," C",".,"," The"," smoothed"," finite"," element"," method"," for"," the"," analysis"," of"," anisotropic"," bodies"," with"," large"," deformation",","," Computers"," Structures",","," ","2","0","0","5",","," ","8","3"],"sub_source":"sci_gen","model":"30B","label":1}