{"text_id":79738,"tokens":["The"," following"," is"," a"," step","-","by","-","step"," guide"," on"," how"," you"," can"," solve"," any"," problem"," using"," the"," method"," known"," as"," \"","Bull","dog","ging","\":","\n","Open"," a"," new"," Excel"," workbook"," and"," make"," two"," worksheets","."," In"," one"," sheet"," (","Bull","dog","gin"," Blues","),"," set"," up"," your"," data"," table"," that"," will"," be"," used"," throughout"," the"," process","."," On"," the"," other"," sheet",","," (","LR"," Chart",",)"," draw"," out"," what"," we"," call"," \"","The"," Lateral"," Relationship"," Chart","\""," which"," shows"," all"," possible"," solutions"," at"," once","."," You"," may"," want"," to"," save"," these"," sheets"," so"," they"," don","'","t"," get"," overwritten"," if"," something"," goes"," wrong"," during"," the"," calculations","."," ","2","."," Click"," File"," >"," Options","..."," from"," within"," Microsoft"," Office"," Excel"," ","2","0","0","7","/","2","0","1","0","/","2","0","1","3","/","2","0","1","6","/","2","0","1","7","/","2","0","1","8","/","2","0","1","9","/","2","0","2","0","/","2","0","2","1","/","2","0","2","2","/","2","0","2","3","/","2","0","0","4","/","2","0","0","5","/","2","0","0","6","/","2","0","0","7","/","2","0","0","8","/","2","0","0","9","/","2","0","1","0","/","2","0","1","1","/","2","0","1","2","/","2","0","1","3","/","2","0","1","4","/","2","0","1","5","/","2","0","1","6","/","2","0","1","7","/","2","0","1","8","/","2","0","1","9","/","2","0","2","0","/","2","1","/","2","2","/","2","3","/","2","4","/","2","5","/","2","6","/","2","7","/","2","8","/","2","9","/","3","0","/","3","1","/","3","2","/","2","0","0","3","/","2","0","0","2","/","2","0","0","1","/","2","0","0","0","/","1","9","9","9","/","1","9","9","8","/","1","9","9","7","/","1","9","9","6"," ","1","9","9","5"," ","1","9","9","4"," ","1","9","9","2"," ","1","9","9","3"," ","1","9","9","6"," ","1","9","9","7"," ","1","9","9","8"," ","1","9","9","9"," ","2","0","0","0"," ","2","0","0","1"," ","2","0","0","2"," ","2","0","0","3"," ","2","0","0","4"," ","2","0","0","5"," ","2","0","0","6"," ","2","0","0","7"," ","2","0","0","8"," ","2","0","0","9"," ","2","0","1","0"," ","2","0","1","1"," ","2","0","1","2"," ","2","0","1","3"," ","2","0","1","4"," ","2","0","1","5"," ","2","0","1","6"," ","2","0","1","7"," ","2","0","1","8"," ","2","0","1","9"," ","2","0","2","0"," ","2","0","2","1"," ","2","0","2","2"," ","2","0","2","3","."," ","3","."," Choose"," Customize"," Ribbon","...."," ","4","."," Check"," off"," the"," box"," next"," to"," Enable"," Developer"," tab","."," ","5","."," Close"," the"," window"," after"," customizing"," the"," ribbon","."," ","6","."," Now"," go"," back"," to"," the"," first"," page"," where"," both"," charts"," were"," created"," and"," select"," the"," whole"," area"," including"," the"," header"," row"," and"," column"," names","."," (","Selecting"," the"," whole"," area"," means"," clicking"," anywhere"," inside"," the"," top"," left"," square",".)"," ","7","."," Right","-","click"," on"," the"," selected"," cells"," and"," choose"," Paste"," Special","..."," (","or"," press"," Ctrl","+","V"," then"," click"," Format",")."," ","8","."," From"," the"," drop","-","down"," menu"," under"," \"","Paste"," Style",":\",","..."],"sub_source":"wikihow","model":"bloomz","label":1}